Workbook
Name aporte: 'Calculadora de Investimento'!$D$20
Name patrimonio: 'Calculadora de Investimento'!$D$23
Name qtd_anos: 'Calculadora de Investimento'!$D$21
Name rendimento_de_carteira: 'Calculadora de Investimento'!$D$16
Name salario: 'Calculadora de Investimento'!$D$15
Name sugestao_investimento: 'Calculadora de Investimento'!$D$17
Name taxa_mensal: 'Calculadora de Investimento'!$D$22

Sheet Tabela de Apoio
A1: Chave | B1: Perfil | C1: Tipo de FII | D1: % | F1: Perfil | G1: %
A2: =B2&"-"&C2 -> Conservador-Papel | B2: Conservador | C2: Papel | D2: 0.3 | F2: Moderado-Tijolo | G2: =VLOOKUP(F2,$A$1:$D$19,4,FALSE) -> 0.35
A3: =B3&"-"&C3 -> Conservador-Tijolo | B3: Conservador | C3: Tijolo | D3: 0.5
A4: =B4&"-"&C4 -> Conservador-Hibridos | B4: Conservador | C4: Hibridos | D4: 0.1
A5: =B5&"-"&C5 -> Conservador-FOF | B5: Conservador | C5: FOF | D5: 0.1
A6: =B6&"-"&C6 -> Conservador-Desenvolvimento | B6: Conservador | C6: Desenvolvimento | D6: 0
A7: =B7&"-"&C7 -> Conservador-Hotelaria | B7: Conservador | C7: Hotelaria | D7: 0
A8: =B8&"-"&C8 -> Moderado-Papel | B8: Moderado | C8: Papel | D8: 0.32
A9: =B9&"-"&C9 -> Moderado-Tijolo | B9: Moderado | C9: Tijolo | D9: 0.35
A10: =B10&"-"&C10 -> Moderado-Hibridos | B10: Moderado | C10: Hibridos | D10: 0.08
A11: =B11&"-"&C11 -> Moderado-FOF | B11: Moderado | C11: FOF | D11: 0.05
A12: =B12&"-"&C12 -> Moderado-Desenvolvimento | B12: Moderado | C12: Desenvolvimento | D12: 0.1
A13: =B13&"-"&C13 -> Moderado-Hotelaria | B13: Moderado | C13: Hotelaria | D13: 0.1
A14: =B14&"-"&C14 -> Agressivo-Papel | B14: Agressivo | C14: Papel | D14: 0.5
... A19: =B19&"-"&C19 -> Agressivo-Hotelaria | B19: Agressivo | C19: Hotelaria | D19: 0.1

Sheet Calculadora de Investimento
B14: Configurações
B15: Salário | D15: 2000
B16: Rendimento de Carteira | D16: 0.006
B17: Sugestão de Investimento (30% do Salário) | D17: =salario*30% -> 600
B19: Investimento Mensal
B20: Quanto investir por mês? | D20: 200
B21: Por quantos anos? | D21: 5
B22: Taxa de Rendimento mensal? | D22: 0.01079
B23: Patrimônio Acumulado? | D23: =FV(taxa_mensal,qtd_anos*12,aporte*-1) -> 16755.383
B24: Dividendos Mensais? | D24: =patrimonio*rendimento_de_carteira -> 100.5323
B26: Cenários | D26: Dividendo
A27: 2 | B27: Quanto teria em 2 anos? | C27: =FV($D$22,$A27*12,$D$20*-1) -> 5445.5255 | D27: =C27*rendimento_de_carteira -> 32.673153
A28: 5 | B28: Quanto teria em 5 anos? | C28: =FV($D$22,$A28*12,$D$20*-1) -> 16755.383 | D28: =C28*rendimento_de_carteira -> 100.5323
A29: 10 | B29: Quanto teria em 10 anos? | C29: =FV($D$22,$A29*12,$D$20*-1) -> 48656.843 | D29: =C29*rendimento_de_carteira -> 291.94106
A30: 20 | B30: Quanto teria em 20 anos? | C30: =FV($D$22,$A30*12,$D$20*-1) -> 225039.68 | D30: =C30*rendimento_de_carteira -> 1350.2381
A31: 30 | B31: Quanto teria em 30 anos? | C31: =FV($D$22,$A31*12,$D$20*-1) -> 864433.93 | D31: =C31*rendimento_de_carteira -> 5186.6036
B33: Perfil | C33: Moderado
B34: Valor a ser investido por mês | C34: =aporte -> 200
B36: Tipo de FII | C36: Percentual Sugerido | D36: Valores
B37: Papel | C37: =VLOOKUP($C$33&"-"&B37,'Tabela de Apoio'!$A:$D,4,FALSE) -> 0.32 | D37: =$C$34*C37 -> 64
B38: Tijolo | C38: =VLOOKUP($C$33&"-"&B38,'Tabela de Apoio'!$A:$D,4,FALSE) -> 0.35 | D38: =$C$34*C38 -> 70
B39: Hibridos | C39: =VLOOKUP($C$33&"-"&B39,'Tabela de Apoio'!$A:$D,4,FALSE) -> 0.08 | D39: =$C$34*C39 -> 16
B40: FOF | C40: =VLOOKUP($C$33&"-"&B40,'Tabela de Apoio'!$A:$D,4,FALSE) -> 0.05 | D40: =$C$34*C40 -> 10
B41: Desenvolvimento | C41: =VLOOKUP($C$33&"-"&B41,'Tabela de Apoio'!$A:$D,4,FALSE) -> 0.1 | D41: =$C$34*C41 -> 20
B42: Hotelaria | C42: =VLOOKUP($C$33&"-"&B42,'Tabela de Apoio'!$A:$D,4,FALSE) -> 0.1 | D42: =$C$34*C42 -> 20
D43: =SUM(D37:D42) -> 200
